basic_stats_distributions/Binomialdistribution.py
basic_stats_distributions/Gaussiandistribution.py
basic_stats_distributions/Generaldistribution.py
basic_stats_distributions/__init__.py
basic_stats_distributions-0.2.dist-info/METADATA
basic_stats_distributions-0.2.dist-info/WHEEL
basic_stats_distributions-0.2.dist-info/license.txt
basic_stats_distributions-0.2.dist-info/top_level.txt
basic_stats_distributions-0.2.dist-info/RECORD
