Metadata-Version: 2.1
Name: basic-stats-distributions
Version: 0.2
Summary: Basic statistical distributions
Home-page: UNKNOWN
Author: Dhyanil Mehta
Author-email: dhyanilm2399@gmail.com
License: UNKNOWN
Platform: UNKNOWN
